aliyunsdkanytrans/__init__.py
aliyunsdkanytrans/request/__init__.py
aliyunsdkanytrans/request/v20250707/BatchTranslateRequest.py
aliyunsdkanytrans/request/v20250707/GetDocTranslateTaskRequest.py
aliyunsdkanytrans/request/v20250707/GetHtmlTranslateTaskRequest.py
aliyunsdkanytrans/request/v20250707/GetImageTranslateTaskRequest.py
aliyunsdkanytrans/request/v20250707/GetLongTextTranslateTaskRequest.py
aliyunsdkanytrans/request/v20250707/SubmitDocTranslateTaskRequest.py
aliyunsdkanytrans/request/v20250707/SubmitHtmlTranslateTaskRequest.py
aliyunsdkanytrans/request/v20250707/SubmitImageTranslateTaskRequest.py
aliyunsdkanytrans/request/v20250707/SubmitLongTextTranslateTaskRequest.py
aliyunsdkanytrans/request/v20250707/TextTranslateRequest.py
aliyunsdkanytrans/request/v20250707/__init__.py
aliyun_python_sdk_anytrans-1.0.0.dist-info/LICENSE
aliyun_python_sdk_anytrans-1.0.0.dist-info/METADATA
aliyun_python_sdk_anytrans-1.0.0.dist-info/WHEEL
aliyun_python_sdk_anytrans-1.0.0.dist-info/top_level.txt
aliyun_python_sdk_anytrans-1.0.0.dist-info/RECORD
